vumi_http_api-0.1.3.dist-info/RECORD
vumi_http_api-0.1.3.dist-info/METADATA
vumi_http_api-0.1.3.dist-info/DESCRIPTION.rst
vumi_http_api-0.1.3.dist-info/top_level.txt
vumi_http_api-0.1.3.dist-info/metadata.json
vumi_http_api-0.1.3.dist-info/WHEEL
vumi_http_api/concurrency_limiter.py
vumi_http_api/resource.py
vumi_http_api/__init__.py
vumi_http_api/auth.py
vumi_http_api/utils.py
vumi_http_api/vumi_api.py
vumi_http_api/tests/test_auth.py
vumi_http_api/tests/test_concurrency_limiter.py
vumi_http_api/tests/__init__.py
vumi_http_api/tests/test_vumi_app.py
vumi_http_api/tests/test_resource.py
